tevcat/__init__.py
tevcat/tevcat_all.py
tevcat/img/allsky_b.png
tevcat/img/allsky_gray.png
tevcat/img/allsky_gray_inv.png
pytevcat-1.3.3.dist-info/METADATA
pytevcat-1.3.3.dist-info/WHEEL
pytevcat-1.3.3.dist-info/top_level.txt
pytevcat-1.3.3.dist-info/RECORD
