Metadata-Version: 2.4
Name: PyTeVCat
Version: 1.3.3
Summary: Python wrapper for TeVCat
Author-email: Akira Okumura <oxon@mac.com>
License: BSD License
Project-URL: Repository, https://github.com/akira-okumura/PyTeVCat.git
Project-URL: Issues, https://github.com/akira-okumura/PyTeVCat/issues
Classifier: Programming Language :: Python :: 3
Classifier: License :: OSI Approved :: BSD License
Classifier: Operating System :: OS Independent
Requires-Dist: numpy
Requires-Dist: astropy
Requires-Dist: future
Requires-Dist: requests
